JWDeviceDB/JWDeviceDB.py
JWDeviceDB/__init__.py
JWDeviceDB-0.0.1.dist-info/LICENSE
JWDeviceDB-0.0.1.dist-info/METADATA
JWDeviceDB-0.0.1.dist-info/WHEEL
JWDeviceDB-0.0.1.dist-info/top_level.txt
JWDeviceDB-0.0.1.dist-info/RECORD
