Metadata-Version: 2.1
Name: JWDeviceDB
Version: 0.0.1
Summary: Device DB
Author-email: JW <JW@dev.null>
Project-URL: Homepage, https://dev.null
Project-URL: Bug Tracker, https://dev.null
Classifier: Programming Language :: Python :: 3
Classifier: License :: OSI Approved :: MIT License
Classifier: Operating System :: OS Independent
Requires-Python: >=3.6
License-File: LICENSE
